odoo/addons/pos_daily_sales_reports_category_only/README.rst
odoo/addons/pos_daily_sales_reports_category_only/__init__.py
odoo/addons/pos_daily_sales_reports_category_only/__manifest__.py
odoo/addons/pos_daily_sales_reports_category_only/i18n/es.po
odoo/addons/pos_daily_sales_reports_category_only/i18n/it.po
odoo/addons/pos_daily_sales_reports_category_only/i18n/pos_daily_sales_reports_category_only.pot
odoo/addons/pos_daily_sales_reports_category_only/models/__init__.py
odoo/addons/pos_daily_sales_reports_category_only/models/pos_config.py
odoo/addons/pos_daily_sales_reports_category_only/models/pos_daily_sales_reports.py
odoo/addons/pos_daily_sales_reports_category_only/models/res_config_settings.py
odoo/addons/pos_daily_sales_reports_category_only/readme/CONTRIBUTORS.rst
odoo/addons/pos_daily_sales_reports_category_only/readme/CREDITS.rst
odoo/addons/pos_daily_sales_reports_category_only/readme/DESCRIPTION.rst
odoo/addons/pos_daily_sales_reports_category_only/static/description/icon.png
odoo/addons/pos_daily_sales_reports_category_only/static/description/index.html
odoo/addons/pos_daily_sales_reports_category_only/static/img/pos_config.png
odoo/addons/pos_daily_sales_reports_category_only/static/img/sample_report.png
odoo/addons/pos_daily_sales_reports_category_only/static/src/xml/SaleDetailsReport.xml
odoo/addons/pos_daily_sales_reports_category_only/tests/__init__.py
odoo/addons/pos_daily_sales_reports_category_only/tests/test_daily_sales_reports.py
odoo/addons/pos_daily_sales_reports_category_only/views/point_of_sale_view.xml
odoo/addons/pos_daily_sales_reports_category_only/views/res_config_settings.xml
odoo_addon_pos_daily_sales_reports_category_only-16.0.1.0.1.dist-info/METADATA
odoo_addon_pos_daily_sales_reports_category_only-16.0.1.0.1.dist-info/WHEEL
odoo_addon_pos_daily_sales_reports_category_only-16.0.1.0.1.dist-info/top_level.txt
odoo_addon_pos_daily_sales_reports_category_only-16.0.1.0.1.dist-info/RECORD
